trainflow/__init__.py
trainflow/core.py
trainflow-0.2.0.dist-info/METADATA
trainflow-0.2.0.dist-info/WHEEL
trainflow-0.2.0.dist-info/top_level.txt
trainflow-0.2.0.dist-info/RECORD
